hifisr_functions/__init__.py
hifisr_functions/annotations.py
hifisr_functions/base.py
hifisr_functions/reads.py
hifisr_functions/references.py
hifisr_functions/reports.py
hifisr_functions/variants.py
hifisr-0.5.0.dist-info/LICENSE
hifisr-0.5.0.dist-info/METADATA
hifisr-0.5.0.dist-info/WHEEL
hifisr-0.5.0.dist-info/top_level.txt
hifisr-0.5.0.dist-info/RECORD
